sconext_ckan/__init__.py
sconext_ckan/ckan.py
sconext_ckan_catalog/__init__.py
sconext_ckan_catalog/ckan_catalog.py
sconext_ckan_catalog/factories/__init__.py
sconext_ckan_catalog/factories/exposed_datasets.py
sconext_ckan_dataservice/__init__.py
sconext_ckan-0.0.0b1.dist-info/METADATA
sconext_ckan-0.0.0b1.dist-info/WHEEL
sconext_ckan-0.0.0b1.dist-info/entry_points.txt
sconext_ckan-0.0.0b1.dist-info/top_level.txt
sconext_ckan-0.0.0b1.dist-info/RECORD
